LICENSE
MANIFEST.in
README.md
requirements.txt
setup.py
some_flask_helpers/__init__.py
some_flask_helpers/blueprint_adapter.py
some_flask_helpers/flask_stopper.py
some_flask_helpers/git_metadata.py
some_flask_helpers.egg-info/PKG-INFO
some_flask_helpers.egg-info/SOURCES.txt
some_flask_helpers.egg-info/dependency_links.txt
some_flask_helpers.egg-info/requires.txt
some_flask_helpers.egg-info/top_level.txt