Metadata-Version: 2.4
Name: some_flask_helpers
Version: 0.2.10
Summary: Generic tools for Flask applications
Home-page: https://github.com/marcus67/some_flask_helpers
Author: Marcus Rickert
Author-email: marcus.rickert@web.de
Requires-Python: >=3.10, <3.14
License-File: LICENSE
Requires-Dist: flask~=2.3.3
Requires-Dist: requests~=2.32.5
Requires-Dist: werkzeug~=3.1.4
Dynamic: author
Dynamic: author-email
Dynamic: description
Dynamic: description-content-type
Dynamic: home-page
Dynamic: license-file
Dynamic: requires-dist
Dynamic: requires-python
Dynamic: summary
